ai_code_assistant/__init__.py
ai_code_assistant/cli.py
ai_code_assistant/config.py
ai_code_assistant/llm.py
ai_code_assistant/py.typed
ai_code_assistant/agent/__init__.py
ai_code_assistant/agent/code_agent.py
ai_code_assistant/agent/code_generator.py
ai_code_assistant/agent/code_reviewer.py
ai_code_assistant/agent/diff_engine.py
ai_code_assistant/agent/file_manager.py
ai_code_assistant/agent/intent_classifier.py
ai_code_assistant/chat/__init__.py
ai_code_assistant/chat/agent_session.py
ai_code_assistant/chat/session.py
ai_code_assistant/context/__init__.py
ai_code_assistant/context/analyzer.py
ai_code_assistant/context/selector.py
ai_code_assistant/editor/__init__.py
ai_code_assistant/editor/diff_handler.py
ai_code_assistant/editor/file_editor.py
ai_code_assistant/editor/prompts.py
ai_code_assistant/generator/__init__.py
ai_code_assistant/generator/code_gen.py
ai_code_assistant/generator/prompts.py
ai_code_assistant/git/__init__.py
ai_code_assistant/git/commit_generator.py
ai_code_assistant/git/manager.py
ai_code_assistant/providers/__init__.py
ai_code_assistant/providers/base.py
ai_code_assistant/providers/cerebras.py
ai_code_assistant/providers/factory.py
ai_code_assistant/providers/google.py
ai_code_assistant/providers/groq.py
ai_code_assistant/providers/ollama.py
ai_code_assistant/providers/openai.py
ai_code_assistant/providers/openrouter.py
ai_code_assistant/refactor/__init__.py
ai_code_assistant/refactor/analyzer.py
ai_code_assistant/refactor/change_plan.py
ai_code_assistant/refactor/multi_file_editor.py
ai_code_assistant/refactor/prompts.py
ai_code_assistant/retrieval/__init__.py
ai_code_assistant/retrieval/chunker.py
ai_code_assistant/retrieval/indexer.py
ai_code_assistant/retrieval/search.py
ai_code_assistant/reviewer/__init__.py
ai_code_assistant/reviewer/analyzer.py
ai_code_assistant/reviewer/prompts.py
ai_code_assistant/utils/__init__.py
ai_code_assistant/utils/file_handler.py
ai_code_assistant/utils/formatters.py
cognify_code-0.2.5.dist-info/licenses/LICENSE
cognify_code-0.2.5.dist-info/METADATA
cognify_code-0.2.5.dist-info/WHEEL
cognify_code-0.2.5.dist-info/entry_points.txt
cognify_code-0.2.5.dist-info/top_level.txt
cognify_code-0.2.5.dist-info/RECORD
