Metadata-Version: 2.4
Name: cognify-code
Version: 0.2.5
Summary: Your local AI-powered code assistant. Review, generate, search, and refactor code with an intelligent AI agent—all running locally with complete privacy.
Author-email: Ashok Kumar <akkssy@users.noreply.github.com>
Maintainer-email: Ashok Kumar <akkssy@users.noreply.github.com>
License: MIT
Project-URL: Homepage, https://akkssy.github.io/cognify-ai-website/
Project-URL: Documentation, https://github.com/akkssy/cognify-ai#readme
Project-URL: Repository, https://github.com/akkssy/cognify-ai
Project-URL: Issues, https://github.com/akkssy/cognify-ai/issues
Project-URL: Changelog, https://github.com/akkssy/cognify-ai/releases
Keywords: ai,code-review,code-generation,code-assistant,ai-agent,langchain,ollama,groq,gemini,cli,developer-tools,refactoring,semantic-search,local-llm,privacy
Classifier: Development Status :: 4 - Beta
Classifier: Environment :: Console
Classifier: Intended Audience :: Developers
Classifier: License :: OSI Approved :: MIT License
Classifier: Operating System :: OS Independent
Classifier: Programming Language :: Python :: 3
Classifier: Programming Language :: Python :: 3.9
Classifier: Programming Language :: Python :: 3.10
Classifier: Programming Language :: Python :: 3.11
Classifier: Programming Language :: Python :: 3.12
Classifier: Topic :: Software Development
Classifier: Topic :: Software Development :: Code Generators
Classifier: Topic :: Software Development :: Quality Assurance
Classifier: Topic :: Software Development :: Testing
Classifier: Topic :: Text Processing :: Linguistic
Classifier: Typing :: Typed
Requires-Python: >=3.9
License-File: LICENSE
Requires-Dist: langchain>=0.1.0
Requires-Dist: langchain-core>=0.1.0
Requires-Dist: langchain-ollama>=0.1.0
Requires-Dist: langchain-openai>=0.1.0
Requires-Dist: click>=8.1.0
Requires-Dist: rich>=13.0.0
Requires-Dist: pyyaml>=6.0
Requires-Dist: pydantic>=2.0.0
Requires-Dist: pydantic-settings>=2.0.0
Requires-Dist: chromadb>=0.4.0
Requires-Dist: sentence-transformers>=2.0.0
Requires-Dist: watchdog>=4.0.0
Provides-Extra: google
Requires-Dist: langchain-google-genai>=1.0.0; extra == "google"
Provides-Extra: groq
Requires-Dist: langchain-groq>=0.1.0; extra == "groq"
Provides-Extra: all-providers
Requires-Dist: langchain-google-genai>=1.0.0; extra == "all-providers"
Requires-Dist: langchain-groq>=0.1.0; extra == "all-providers"
Provides-Extra: dev
Requires-Dist: pytest>=7.0.0; extra == "dev"
Requires-Dist: pytest-asyncio>=0.21.0; extra == "dev"
Requires-Dist: pytest-mock>=3.10.0; extra == "dev"
Requires-Dist: black>=23.0.0; extra == "dev"
Requires-Dist: ruff>=0.1.0; extra == "dev"
Requires-Dist: mypy>=1.0.0; extra == "dev"
Requires-Dist: build>=1.0.0; extra == "dev"
Requires-Dist: twine>=4.0.0; extra == "dev"
Dynamic: license-file
